{
  "workouts": [
    {
      "id": 1,
      "type": "Swim",
      "description": "Ladders",
      "duration": "00:51:00",
      "distance": "2500 m",
      "date": "09/02/2019"
    },
    {
      "id": 2,
      "type": "Bike",
      "description": "Cruise",
      "duration": "00:30:00",
      "distance": "10 mi",
      "date": "09/03/2019"
    },
    {
      "id": 3,
      "type": "Run",
      "description": "Intervals",
      "duration": "00:45:00",
      "distance": "5.5 mi",
      "date": "09/04/2019"
    },
    {
      "description": "new",
      "date": "new",
      "type": "new",
      "duration": "new",
      "distance": "new",
      "id": 4
    },
    {
      "description": "Intervals again",
      "date": "09/18/2019",
      "type": "Swim",
      "duration": "00:45:00",
      "distance": "2500 m",
      "id": 5
    },
    {
      "description": "a",
      "date": "2019-09-18",
      "type": "",
      "duration": "01:01",
      "distance": "2500 m",
      "id": 6
    }
  ]
}